remcmp/__init__.py
remcmp/__main__.py
remcmp/remcmp.py
remcmp-2.1.0.post2.dist-info/LICENSE
remcmp-2.1.0.post2.dist-info/METADATA
remcmp-2.1.0.post2.dist-info/WHEEL
remcmp-2.1.0.post2.dist-info/entry_points.txt
remcmp-2.1.0.post2.dist-info/top_level.txt
remcmp-2.1.0.post2.dist-info/RECORD
