Metadata-Version: 2.1
Name: remcmp
Version: 2.1.0.post2
Summary: Extensible program to compare local and remote directories.
Home-page: https://github.com/DimiDimit/remcmp
Author: DimiDimit
Author-email: dmtrdmtrov@gmail.com
License: UNKNOWN
Platform: UNKNOWN
Classifier: Environment :: Console
Classifier: License :: OSI Approved :: MIT License
Classifier: Natural Language :: English
Classifier: Operating System :: OS Independent
Classifier: Programming Language :: Python :: 3 :: Only
Classifier: Topic :: System :: Filesystems
Classifier: Topic :: Utilities
Requires-Python: >=3.7
Requires-Dist: colorama
Requires-Dist: fs
